django_firebase_custom_auth/__init__.py
django_firebase_custom_auth/app_settings.py
django_firebase_custom_auth/firebase.py
django_firebase_custom_auth/serializers.py
django_firebase_custom_auth/urls.py
django_firebase_custom_auth/views.py
django_firebase_custom_auth-0.1.dist-info/LICENSE
django_firebase_custom_auth-0.1.dist-info/METADATA
django_firebase_custom_auth-0.1.dist-info/WHEEL
django_firebase_custom_auth-0.1.dist-info/top_level.txt
django_firebase_custom_auth-0.1.dist-info/RECORD
